kn_sock/__init__.py
kn_sock/cli.py
kn_sock/compression.py
kn_sock/config.py
kn_sock/decorators.py
kn_sock/errors.py
kn_sock/file_transfer.py
kn_sock/http.py
kn_sock/interactive_cli.py
kn_sock/json_socket.py
kn_sock/live_stream.py
kn_sock/load_balancer.py
kn_sock/protobuf.py
kn_sock/pubsub.py
kn_sock/queue.py
kn_sock/rpc.py
kn_sock/tcp.py
kn_sock/udp.py
kn_sock/utils.py
kn_sock/video_chat.py
kn_sock/websocket.py
kn_sock/network/__init__.py
kn_sock/network/arp.py
kn_sock/network/mac_lookup.py
kn_sock/network/monitor.py
kn_sock-0.3.0.dist-info/licenses/LICENSE
kn_sock-0.3.0.dist-info/METADATA
kn_sock-0.3.0.dist-info/WHEEL
kn_sock-0.3.0.dist-info/entry_points.txt
kn_sock-0.3.0.dist-info/top_level.txt
kn_sock-0.3.0.dist-info/RECORD
