Metadata-Version: 2.4
Name: kn-sock
Version: 0.3.0
Summary: Modern Python networking library with comprehensive protocol support and developer-friendly APIs
Home-page: https://github.com/KhagendraN/kn-sock
Author: Khagendra Neupane
Author-email: nkhagendra1@gmail.com
Classifier: Programming Language :: Python :: 3
Classifier: License :: OSI Approved :: MIT License
Classifier: Operating System :: OS Independent
Requires-Python: >=3.6
License-File: LICENSE
Requires-Dist: opencv-python
Requires-Dist: numpy
Requires-Dist: pyaudio
Requires-Dist: ffmpeg-python
Dynamic: author
Dynamic: author-email
Dynamic: classifier
Dynamic: description
Dynamic: description-content-type
Dynamic: home-page
Dynamic: license-file
Dynamic: requires-dist
Dynamic: requires-python
Dynamic: summary
